uhubspot/auth.py
uhubspot/client.py
uhubspot/client.pyi
uhubspot/components/__init__.py
uhubspot/components/schemas/__init__.py
uhubspot/components/schemas/association.py
uhubspot/components/schemas/association_type.py
uhubspot/components/schemas/object_id_ref.py
uhubspot/components/schemas/object_type.py
uhubspot/openapi.yaml
uhubspot/paths/__init__.py
uhubspot/paths/batchGetAssociations/__init__.py
uhubspot/paths/batchGetAssociations/param_model.py
uhubspot/paths/batchGetAssociations/request_body.py
uhubspot/paths/batchGetAssociations/response_body.py
uhubspot/paths/getAssociations/__init__.py
uhubspot/paths/getAssociations/param_model.py
uhubspot/paths/getAssociations/response_body.py
uhubspot/py.typed
hubspot_unofficial-0.1.0.dist-info/WHEEL
hubspot_unofficial-0.1.0.dist-info/METADATA
hubspot_unofficial-0.1.0.dist-info/RECORD
