Metadata-Version: 2.1
Name: hubspot-unofficial
Version: 0.1.0
Summary: Reverse-engineered HubSpot client
License: MIT
Requires-Python: >=3.9,<4.0
Classifier: License :: OSI Approved :: MIT License
Classifier: Programming Language :: Python :: 3
Classifier: Programming Language :: Python :: 3.9
Classifier: Programming Language :: Python :: 3.10
Classifier: Programming Language :: Python :: 3.11
Requires-Dist: lapidary (>=0.7.3,<0.8.0)
